pre_commit_tool/__init__.py
pre_commit_tool/__main__.py
pre_commit_tool/main.py
pre_commit_tool/simplecli.py
pre_commit_tool-0.1.8.dist-info/METADATA
pre_commit_tool-0.1.8.dist-info/WHEEL
pre_commit_tool-0.1.8.dist-info/entry_points.txt
pre_commit_tool-0.1.8.dist-info/licenses/LICENSE
pre_commit_tool-0.1.8.dist-info/RECORD
