Metadata-Version: 2.3
Name: pre-commit-tool
Version: 0.1.8
Summary: Very simple human-friendlier wrapper around pre-commit
Project-URL: Repository, https://github.com/jmknoble/pre-commit-tool
Author-email: jmknoble <jmknoble@pobox.com>
License: MIT License
Keywords: cli,git,pre-commit
Classifier: Development Status :: 4 - Beta
Classifier: Environment :: Console
Classifier: License :: OSI Approved :: MIT License
Classifier: Operating System :: OS Independent
Classifier: Programming Language :: Python :: 3
Classifier: Topic :: Software Development
Classifier: Topic :: Utilities
Requires-Python: >=3.10
